calibre/__init__.py
calibre/base.py
calibre/calibrators/__init__.py
calibre/calibrators/cdi_iso.py
calibre/calibrators/isotonic.py
calibre/calibrators/nearly_isotonic.py
calibre/calibrators/regularized.py
calibre/calibrators/relaxed_pava.py
calibre/calibrators/smoothed.py
calibre/calibrators/spline.py
calibre/diagnostics.py
calibre/metrics.py
calibre/py.typed
calibre/utils/__init__.py
calibre/utils/array_ops.py
calibre/utils/validation.py
calibre/visualization.py
calibre-0.6.0.dist-info/WHEEL
calibre-0.6.0.dist-info/METADATA
calibre-0.6.0.dist-info/RECORD
