Metadata-Version: 2.3
Name: calibre
Version: 0.6.0
Summary: Advanced probability calibration techniques for machine learning models
Author: Gaurav Sood
Author-email: Gaurav Sood <gsood07@gmail.com>
License: MIT
Classifier: Programming Language :: Python :: 3
Classifier: Programming Language :: Python :: 3.12
Classifier: Programming Language :: Python :: 3.13
Classifier: Programming Language :: Python :: 3.14
Classifier: License :: OSI Approved :: MIT License
Classifier: Operating System :: OS Independent
Classifier: Topic :: Scientific/Engineering :: Artificial Intelligence
Classifier: Topic :: Scientific/Engineering :: Mathematics
Classifier: Topic :: Scientific/Engineering :: Information Analysis
Requires-Dist: numpy>=1.20.0
Requires-Dist: scipy>=1.7.0
Requires-Dist: scikit-learn>=1.0.0
Requires-Dist: cvxpy>=1.2.0
Requires-Dist: pandas>=1.3.0
Requires-Dist: matplotlib>=3.4.0
Requires-Dist: seaborn>=0.11.0
Requires-Dist: sphinx>=7.0 ; extra == 'docs'
Requires-Dist: furo>=2024.1.29 ; extra == 'docs'
Requires-Dist: sphinx-autodoc-typehints>=1.25 ; extra == 'docs'
Requires-Dist: sphinx-copybutton>=0.5 ; extra == 'docs'
Requires-Dist: myst-parser>=2.0 ; extra == 'docs'
Requires-Dist: nbsphinx>=0.9.0 ; extra == 'docs'
Requires-Dist: ipykernel>=6.0 ; extra == 'docs'
Requires-Python: >=3.12
Project-URL: Bug Tracker, https://github.com/finite-sample/calibre/issues
Project-URL: Documentation, https://finite-sample.github.io/calibre/
Project-URL: Homepage, https://github.com/finite-sample/calibre
Project-URL: Repository, https://github.com/finite-sample/calibre
Provides-Extra: docs
